LICENSE.txt
MANIFEST.in
README.md
setup.py
python/jittor/__init__.py
python/jittor/__init__.pyi
python/jittor/attention.py
python/jittor/compile_extern.py
python/jittor/compiler.py
python/jittor/contrib.py
python/jittor/depthwise_conv.py
python/jittor/distributions.py
python/jittor/init.py
python/jittor/init_cupy.py
python/jittor/linalg.py
python/jittor/lr_scheduler.py
python/jittor/misc.py
python/jittor/nn.py
python/jittor/optim.py
python/jittor/pool.py
python/jittor/pyjt_compiler.py
python/jittor/sparse.py
python/jittor/version
python/jittor/weightnorm.py
python/jittor.egg-info/PKG-INFO
python/jittor.egg-info/SOURCES.txt
python/jittor.egg-info/dependency_links.txt
python/jittor.egg-info/requires.txt
python/jittor.egg-info/top_level.txt
python/jittor/ccl/__init__.py
python/jittor/ccl/ccl_2d.py
python/jittor/ccl/ccl_3d.py
python/jittor/ccl/ccl_link.py
python/jittor/dataset/__init__.py
python/jittor/dataset/cifar.py
python/jittor/dataset/dataset.py
python/jittor/dataset/mnist.py
python/jittor/dataset/sampler.py
python/jittor/dataset/utils.py
python/jittor/dataset/voc.py
python/jittor/demo/simple_cgan.py
python/jittor/einops/__init__.py
python/jittor/einops/_backends.py
python/jittor/einops/einops.py
python/jittor/einops/parsing.py
python/jittor/einops/experimental/__init__.py
python/jittor/einops/experimental/indexing.py
python/jittor/einops/layers/__init__.py
python/jittor/einops/layers/_einmix.py
python/jittor/einops/layers/jittor.py
python/jittor/extern/acl/acl_compiler.py
python/jittor/extern/acl/acl_error_code.cc
python/jittor/extern/acl/acl_jittor.cc
python/jittor/extern/acl/acl_jittor.h
python/jittor/extern/acl/acl_op_exec.cc
python/jittor/extern/acl/aclnn/aclnn.cc
python/jittor/extern/acl/aclnn/aclnn.h
python/jittor/extern/acl/aclops/__init__.py
python/jittor/extern/acl/aclops/aclops.h
python/jittor/extern/acl/aclops/base_op.h
python/jittor/extern/acl/aclops/base_op_acl.cc
python/jittor/extern/acl/aclops/binary_op_acl.cc
python/jittor/extern/acl/aclops/binary_op_acl.h
python/jittor/extern/acl/aclops/bmm_op.py
python/jittor/extern/acl/aclops/bmm_op_acl.cc
python/jittor/extern/acl/aclops/bmm_op_acl.h
