Metadata-Version: 2.1
Name: jittor
Version: 1.3.10.0
Summary: a Just-in-time(JIT) deep learning framework
Home-page: http://jittor.org
Author: Jittor Group
Author-email: ran.donglang@gmail.com
Requires-Python: >=3.7
License-File: LICENSE.txt
Requires-Dist: numpy<2.0
Requires-Dist: tqdm
Requires-Dist: pillow
Requires-Dist: astunparse
Requires-Dist: pywin32>=1.0; platform_system == "Windows"
